{
  "version": 1,
  "license": "CC-BY-SA-3.0",
  "copyright": "by malanisa (discord)",
  "size": {
    "x": 32,
    "y": 32
  },
  "states": [
    {
      "name": "big"
    },
    {
      "name": "medium"
    },
    {
      "name": "small"
    },
    {
      "name": "big_R"
    },
    {
      "name": "medium_R"
    },
    {
      "name": "small_R"
    },
    {
      "name": "shard"
    },
    {
      "name": "shard2"
    },
    {
      "name": "shard3"
    },
    {
      "name": "shard4"
    }
  ]
}
